<Properties GitUserInfo="UsingGIT" StartupConfiguration="{D12AE5B9-D096-4A92-AA51-DDEF6CB6524E}|https">
  <MonoDevelop.Ide.ItemProperties.TX__Luminescence PreferredExecutionTarget="/Applications/Google Chrome.app" />
  <MultiItemStartupConfigurations />
  <MonoDevelop.Ide.DebuggingService.PinnedWatches />
  <MonoDevelop.Ide.Workspace ActiveConfiguration="Debug" />
  <MonoDevelop.Ide.Workbench ActiveDocument="TX-Luminescence/Views/Shared/_Layout.cshtml">
    <Files>
      <File FileName="TX-Luminescence/Views/Shared/_Layout.cshtml" Line="136" Column="49" IsPinned="True" />
      <File FileName="TX-Luminescence/wwwroot/lib/twitter-bootstrap/css/bootstrap.css" Line="4059" Column="2" />
    </Files>
    <Pads>
      <Pad Id="ProjectPad">
        <State name="__root__">
          <Node name="TX_Luminescence">
            <Node name="TX_Luminescence">
              <Node name="Views" expanded="True">
                <Node name="Shared" expanded="True">
                  <Node name="_Layout.cshtml" selected="True" />
                </Node>
              </Node>
              <Node name="wwwroot" expanded="True">
                <Node name="lib" expanded="True" />
              </Node>
            </Node>
          </Node>
        </State>
      </Pad>
    </Pads>
  </MonoDevelop.Ide.Workbench>
  <MonoDevelop.Ide.DebuggingService.Breakpoints>
    <BreakpointStore />
  </MonoDevelop.Ide.DebuggingService.Breakpoints>
</Properties>